trackastra/__init__.py
trackastra/_version.py
trackastra/cli.py
trackastra/data/__init__.py
trackastra/data/_check_ctc.py
trackastra/data/_compute_overlap.py
trackastra/data/augmentations.py
trackastra/data/data.py
trackastra/data/distributed.py
trackastra/data/example_data.py
trackastra/data/features.py
trackastra/data/matching.py
trackastra/data/utils.py
trackastra/data/wrfeat.py
trackastra/data/resources/Fluo-N3DH-CHO_02_ERR_SEG.tif
trackastra/data/resources/Fluo-N3DH-CHO_02_img.tif
trackastra/data/resources/Fluo_Hela_02_ERR_SEG.tif
trackastra/data/resources/Fluo_Hela_02_img.tif
trackastra/data/resources/trpL_150310-11_img.tif
trackastra/data/resources/trpL_150310-11_mask.tif
trackastra/model/__init__.py
trackastra/model/model.py
trackastra/model/model_api.py
trackastra/model/model_parts.py
trackastra/model/predict.py
trackastra/model/pretrained.json
trackastra/model/pretrained.py
trackastra/model/rope.py
trackastra/tracking/__init__.py
trackastra/tracking/ilp.py
trackastra/tracking/track_graph.py
trackastra/tracking/tracking.py
trackastra/tracking/utils.py
trackastra/utils/__init__.py
trackastra/utils/utils.py
trackastra-0.5.2.dist-info/licenses/LICENSE
trackastra-0.5.2.dist-info/METADATA
trackastra-0.5.2.dist-info/WHEEL
trackastra-0.5.2.dist-info/entry_points.txt
trackastra-0.5.2.dist-info/top_level.txt
trackastra-0.5.2.dist-info/RECORD
