Metadata-Version: 2.4
Name: trackastra
Version: 0.5.2
Summary: Tracking by Association with Transformers
Author: Benjamin Gallusser, Martin Weigert
Author-email: bgallusser@gmail.com, marweigert@gmail.com
License: BSD 3-Clause License
Classifier: Development Status :: 3 - Alpha
Classifier: Intended Audience :: Science/Research
Classifier: Topic :: Scientific/Engineering
Classifier: License :: OSI Approved :: BSD License
Classifier: Programming Language :: Python :: 3.10
Classifier: Programming Language :: Python :: 3.11
Classifier: Programming Language :: Python :: 3.12
Classifier: Programming Language :: Python :: 3.13
Requires-Python: >=3.10
License-File: LICENSE
Requires-Dist: numpy
Requires-Dist: scipy
Requires-Dist: pandas
Requires-Dist: scikit-image
Requires-Dist: torch
Requires-Dist: torchvision
Requires-Dist: pyyaml
Requires-Dist: edt
Requires-Dist: joblib
Requires-Dist: lz4
Requires-Dist: imagecodecs>=2023.7.10
Requires-Dist: chardet
Requires-Dist: dask
Requires-Dist: numba
Requires-Dist: geff>=1
Requires-Dist: tqdm
Requires-Dist: requests
Requires-Dist: psutil
Requires-Dist: platformdirs
Provides-Extra: ilp
Requires-Dist: motile>=0.3; extra == "ilp"
Provides-Extra: dev
Requires-Dist: pytest; extra == "dev"
Requires-Dist: ruff; extra == "dev"
Requires-Dist: black; extra == "dev"
Requires-Dist: mypy; extra == "dev"
Requires-Dist: pre-commit; extra == "dev"
Requires-Dist: twine; extra == "dev"
Requires-Dist: build; extra == "dev"
Provides-Extra: train
Requires-Dist: lightning; extra == "train"
Requires-Dist: wandb; extra == "train"
Requires-Dist: tensorboard; extra == "train"
Requires-Dist: configargparse; extra == "train"
Requires-Dist: humanize; extra == "train"
Requires-Dist: matplotlib; extra == "train"
Requires-Dist: kornia>=0.7.0; extra == "train"
Requires-Dist: gitpython; extra == "train"
Provides-Extra: all
Requires-Dist: trackastra[dev,ilp,train]; extra == "all"
Provides-Extra: test
Requires-Dist: pytest; extra == "test"
Provides-Extra: etultra
Requires-Dist: trackastra_pretrained_feats; extra == "etultra"
Dynamic: license-file
